finetuner_stubs-0.13.10-nspkg.pth
_finetuner/excepts/__init__.py
_finetuner/runner/stubs/__init__.py
_finetuner/runner/stubs/callback.py
_finetuner/runner/stubs/config.py
_finetuner/runner/stubs/model.py
finetuner_stubs-0.13.10.dist-info/METADATA
finetuner_stubs-0.13.10.dist-info/WHEEL
finetuner_stubs-0.13.10.dist-info/namespace_packages.txt
finetuner_stubs-0.13.10.dist-info/top_level.txt
finetuner_stubs-0.13.10.dist-info/RECORD
